tapioca_camara/__init__.py
tapioca_camara/resource_mapping.py
tapioca_camara/tapioca_camara.py
tapioca_camara-0.3.0.dist-info/LICENSE
tapioca_camara-0.3.0.dist-info/METADATA
tapioca_camara-0.3.0.dist-info/WHEEL
tapioca_camara-0.3.0.dist-info/top_level.txt
tapioca_camara-0.3.0.dist-info/RECORD
